{"name":"build-javascript","namedChunkGroups":{"app":{"name":"app","assets":[{"name":"webpack-runtime-fa29f4536bc29bdd045d.js","size":3873},{"name":"framework-3114d7246739e4a62d45.js","size":140729},{"name":"app-f52c0b1c28cf7bbfcb7f.js","size":81344}],"filteredAssets":0,"assetsSize":225946,"filteredAuxiliaryAssets":3,"auxiliaryAssetsSize":712716},"component---src-pages-404-tsx":{"name":"component---src-pages-404-tsx","assets":[{"name":"component---src-pages-404-tsx-61c9637489e75ce70c47.js","size":728}],"filteredAssets":0,"assetsSize":728,"filteredAuxiliaryAssets":1,"auxiliaryAssetsSize":1978},"component---src-pages-index-tsx":{"name":"component---src-pages-index-tsx","assets":[{"name":"ee8b1517-c5b0a799a65c4605571b.js","size":85492},{"name":"component---src-pages-index-tsx-1be3c15d5140d383d28b.js","size":361454}],"filteredAssets":0,"assetsSize":446946,"filteredAuxiliaryAssets":2,"auxiliaryAssetsSize":2054108}},"assetsByChunkName":{"app":["webpack-runtime-fa29f4536bc29bdd045d.js","framework-3114d7246739e4a62d45.js","app-f52c0b1c28cf7bbfcb7f.js"],"component---src-pages-404-tsx":["component---src-pages-404-tsx-61c9637489e75ce70c47.js"],"component---src-pages-index-tsx":["ee8b1517-c5b0a799a65c4605571b.js","component---src-pages-index-tsx-1be3c15d5140d383d28b.js"]},"childAssetsByChunkName":{}}